bowtie2qc/__init__.py
bowtie2qc/bowtie2QC.py
bowtie2qc/bowtie2QCPlot.py
bowtie2qc-0.0.2.dist-info/METADATA
bowtie2qc-0.0.2.dist-info/WHEEL
bowtie2qc-0.0.2.dist-info/top_level.txt
bowtie2qc-0.0.2.dist-info/RECORD
