Metadata-Version: 2.1
Name: bowtie2qc
Version: 0.0.2
Summary: A python bowtie2 QC ploter
Home-page: https://github.com/whuang022ai/bowtie2QC
Download-URL: https://pypi.org/project/bowtie2QC/
Author: MING HAN YANG
Author-email: whuang022@gmail.com
License: Apache 2.0
Classifier: Programming Language :: Python :: 3.7
Classifier: Programming Language :: Python :: 3.8
Classifier: Programming Language :: Python :: 3.9
Classifier: Programming Language :: Python :: 3.10
Classifier: Programming Language :: Python :: 3.11
Requires-Python: >=3.11.5
Requires-Dist: matplotlib >=3.8.4
Requires-Dist: pandas >=2.2.3
Provides-Extra: dev
